raymond/__init__.py
raymond/version.py
raymond/say/__init__.py
raymond-0.0.3.dist-info/LICENSE
raymond-0.0.3.dist-info/METADATA
raymond-0.0.3.dist-info/WHEEL
raymond-0.0.3.dist-info/top_level.txt
raymond-0.0.3.dist-info/RECORD
