Metadata-Version: 2.1
Name: raymond
Version: 0.0.3
Summary: Suite of utilities created by Raymond Tunstill.
Home-page: https://raymondkirk.github.io/raymond/
Author: Raymond Tunstill
Author-email: ray.tunstill@live.co.uk
License: GNU GPLv3
Platform: UNKNOWN
Classifier: Programming Language :: Python :: 3
Requires-Python: >=3.7
License-File: LICENSE
